jankenschema/__init__.py
jankenschema/db_column.py
jankenschema/gen_common.py
jankenschema/gen_rt.py
jankenschema/gen_ts.py
jankenschema/generate_code.py
jankenschema/main.py
jankenschema/read.py
jankenschema/utils.py
jankenschema-0.1.8.dist-info/LICENSE
jankenschema-0.1.8.dist-info/METADATA
jankenschema-0.1.8.dist-info/WHEEL
jankenschema-0.1.8.dist-info/entry_points.txt
jankenschema-0.1.8.dist-info/RECORD
